{"ventnor-classic":{"coord":{"lon":-73.9956,"lat":40.7505},"weather":[{"id":803,"main":"Clouds","description":"broken clouds","icon":"04d"}],"base":"stations","main":{"temp":277.55,"feels_like":276.05,"temp_min":274.64,"temp_max":279.38,"pressure":1021,"humidity":73},"visibility":10000,"wind":{"speed":1.79,"deg":360,"gust":3.58},"clouds":{"all":75},"dt":1647003457,"sys":{"type":2,"id":2003558,"country":"US","sunrise":1646997258,"sunset":1647039473},"timezone":-18000,"id":5106184,"name":"Weehawken","cod":200}}
