{"funky-pickle-philly":{"coord":{"lon":-75.1593,"lat":39.9516},"weather":[{"id":804,"main":"Clouds","description":"overcast clouds","icon":"04d"}],"base":"stations","main":{"temp":296.19,"feels_like":296.09,"temp_min":295.03,"temp_max":297.3,"pressure":1005,"humidity":59},"visibility":10000,"wind":{"speed":11.32,"deg":220,"gust":18.01},"clouds":{"all":100},"dt":1646678106,"sys":{"type":2,"id":2037403,"country":"US","sunrise":1646652298,"sunset":1646693917},"timezone":-18000,"id":4560349,"name":"Philadelphia","cod":200},"ventnor-classic":{"coord":{"lon":-74.0014,"lat":40.7547},"weather":[{"id":803,"main":"Clouds","description":"broken clouds","icon":"04d"}],"base":"stations","main":{"temp":294.46,"feels_like":294.11,"temp_min":285.87,"temp_max":297.74,"pressure":1004,"humidity":56},"visibility":10000,"wind":{"speed":10.29,"deg":220,"gust":15.43},"clouds":{"all":75},"dt":1646678592,"sys":{"type":2,"id":2003558,"country":"US","sunrise":1646652048,"sunset":1646693612},"timezone":-18000,"id":5106184,"name":"Weehawken","cod":200},"west-hampton-cup":{"coord":{"lon":-74.0014,"lat":40.7547},"weather":[{"id":803,"main":"Clouds","description":"broken clouds","icon":"04d"}],"base":"stations","main":{"temp":294.46,"feels_like":294.11,"temp_min":285.87,"temp_max":297.74,"pressure":1004,"humidity":56},"visibility":10000,"wind":{"speed":10.29,"deg":220,"gust":15.43},"clouds":{"all":75},"dt":1646678592,"sys":{"type":2,"id":2003558,"country":"US","sunrise":1646652048,"sunset":1646693612},"timezone":-18000,"id":5106184,"name":"Weehawken","cod":200}}
