{"another-event-for-pickleball":{"coord":{"lon":-75.5227,"lat":39.1566},"weather":[{"id":800,"main":"Clear","description":"clear sky","icon":"01n"}],"base":"stations","main":{"temp":273.85,"feels_like":268.05,"temp_min":273.1,"temp_max":274.79,"pressure":1004,"humidity":64},"visibility":10000,"wind":{"speed":7.2,"deg":270},"clouds":{"all":0},"dt":1642488249,"sys":{"type":1,"id":3847,"country":"US","sunrise":1642508308,"sunset":1642543570},"timezone":-18000,"id":4142290,"name":"Dover","cod":200},"the-allstar-pickleball-finals":{"coord":{"lon":-74.0028,"lat":40.7544},"weather":[{"id":804,"main":"Clouds","description":"overcast clouds","icon":"04n"}],"base":"stations","main":{"temp":273.74,"feels_like":268.12,"temp_min":271.88,"temp_max":274.93,"pressure":999,"humidity":61},"visibility":10000,"wind":{"speed":6.71,"deg":360,"gust":14.75},"clouds":{"all":100},"dt":1642487714,"sys":{"type":2,"id":2003558,"country":"US","sunrise":1642508192,"sunset":1642542957},"timezone":-18000,"id":5106184,"name":"Weehawken","cod":200},"santas-pickleball-battle-royal":{"coord":{"lon":-156.7861,"lat":71.2911},"weather":[{"id":721,"main":"Haze","description":"haze","icon":"50n"},{"id":601,"main":"Snow","description":"snow","icon":"13n"}],"base":"stations","main":{"temp":250.16,"feels_like":243.16,"temp_min":250.16,"temp_max":250.16,"pressure":1021,"humidity":70},"visibility":9656,"wind":{"speed":4.12,"deg":350},"snow":{"1h":0.51},"clouds":{"all":100},"dt":1642488249,"sys":{"type":1,"id":7649,"country":"US","sunrise":0,"sunset":0},"timezone":-32400,"id":5880054,"name":"Barrow","cod":200},"pay-your-taxes-pickleball-showdown":{"coord":{"lon":-77.0349,"lat":38.8891},"weather":[{"id":804,"main":"Clouds","description":"overcast clouds","icon":"04n"}],"base":"stations","main":{"temp":273.97,"feels_like":273.97,"temp_min":272.71,"temp_max":275.11,"pressure":1007,"humidity":61},"visibility":10000,"wind":{"speed":0.89,"deg":293,"gust":5.36},"clouds":{"all":100},"dt":1642488249,"sys":{"type":2,"id":2002287,"country":"US","sunrise":1642508630,"sunset":1642543974},"timezone":-18000,"id":4140963,"name":"Washington D.C.","cod":200},"yet-another-new-event":{"coord":{"lon":-122.4198,"lat":37.7649},"weather":[{"id":802,"main":"Clouds","description":"scattered clouds","icon":"03n"}],"base":"stations","main":{"temp":283.8,"feels_like":283.11,"temp_min":280.85,"temp_max":286.02,"pressure":1018,"humidity":84},"visibility":10000,"wind":{"speed":1.79,"deg":230,"gust":4.47},"clouds":{"all":40},"dt":1642488250,"sys":{"type":2,"id":2016474,"country":"US","sunrise":1642432978,"sunset":1642468577},"timezone":-28800,"id":5391959,"name":"San Francisco","cod":200}}
