{"another-event-for-pickleball":{"coord":{"lon":-75.5244,"lat":39.1582},"weather":[{"id":701,"main":"Mist","description":"mist","icon":"50d"}],"base":"stations","main":{"temp":273.18,"feels_like":269.61,"temp_min":271.45,"temp_max":275.2,"pressure":1016,"humidity":99},"visibility":4828,"wind":{"speed":3.09,"deg":270},"clouds":{"all":0},"dt":1644324610,"sys":{"type":2,"id":2043208,"country":"US","sunrise":1644321720,"sunset":1644359440},"timezone":-18000,"id":4142290,"name":"Dover","cod":200},"santas-pickleball-battle-royal":{"coord":{"lon":-156.7861,"lat":71.2911},"weather":[{"id":801,"main":"Clouds","description":"few clouds","icon":"02n"}],"base":"stations","main":{"temp":236.38,"feels_like":229.38,"temp_min":236.38,"temp_max":236.38,"pressure":1026,"humidity":100,"sea_level":1026,"grnd_level":1026},"visibility":10000,"wind":{"speed":3.18,"deg":53,"gust":3.29},"clouds":{"all":16},"dt":1644324858,"sys":{"country":"US","sunrise":1644349881,"sunset":1644370285},"timezone":-32400,"id":5880054,"name":"Barrow","cod":200},"pay-your-taxes-pickleball-showdown":{"coord":{"lon":-77.0285,"lat":38.8874},"weather":[{"id":802,"main":"Clouds","description":"scattered clouds","icon":"03d"}],"base":"stations","main":{"temp":272.49,"feels_like":272.49,"temp_min":270.4,"temp_max":274.87,"pressure":1017,"humidity":81},"visibility":10000,"wind":{"speed":0.89,"deg":319,"gust":2.24},"clouds":{"all":40},"dt":1644324645,"sys":{"type":2,"id":2036309,"country":"US","sunrise":1644322052,"sunset":1644359829},"timezone":-18000,"id":4140963,"name":"Washington D.C.","cod":200},"yet-another-new-event":{"coord":{"lon":-122.4198,"lat":37.7649},"weather":[{"id":801,"main":"Clouds","description":"few clouds","icon":"02n"}],"base":"stations","main":{"temp":283.28,"feels_like":282.44,"temp_min":278.11,"temp_max":287.25,"pressure":1023,"humidity":80},"visibility":10000,"wind":{"speed":1.79,"deg":110,"gust":3.13},"clouds":{"all":20},"dt":1644324859,"sys":{"type":2,"id":2010146,"country":"US","sunrise":1644332823,"sunset":1644370846},"timezone":-28800,"id":5391959,"name":"San Francisco","cod":200}}
