{"another-event-for-pickleball":{"coord":{"lon":-75.5214,"lat":39.156},"weather":[{"id":801,"main":"Clouds","description":"few clouds","icon":"02d"}],"base":"stations","main":{"temp":292.64,"feels_like":292.24,"temp_min":287.03,"temp_max":294.2,"pressure":1018,"humidity":61},"visibility":10000,"wind":{"speed":8.75,"deg":180},"clouds":{"all":20},"dt":1645123216,"sys":{"type":1,"id":3847,"country":"US","sunrise":1645098685,"sunset":1645137663},"timezone":-18000,"id":4142290,"name":"Dover","cod":200},"ventnor-classic":{"coord":{"lon":-74.0017,"lat":40.7545},"weather":[{"id":801,"main":"Clouds","description":"few clouds","icon":"02d"}],"base":"stations","main":{"temp":288.28,"feels_like":287.31,"temp_min":281.99,"temp_max":293.3,"pressure":1020,"humidity":56},"visibility":10000,"wind":{"speed":12.35,"deg":220,"gust":15.43},"clouds":{"all":20},"dt":1645122988,"sys":{"type":2,"id":2003558,"country":"US","sunrise":1645098454,"sunset":1645137165},"timezone":-18000,"id":5106184,"name":"Weehawken","cod":200},"santas-pickleball-battle-royal":{"coord":{"lon":-156.7861,"lat":71.2911},"weather":[{"id":602,"main":"Snow","description":"heavy snow","icon":"13n"}],"base":"stations","main":{"temp":250.16,"feels_like":243.16,"temp_min":250.16,"temp_max":250.16,"pressure":1028,"humidity":70},"visibility":6437,"wind":{"speed":5.14,"deg":260},"snow":{"1h":5.59},"clouds":{"all":100},"dt":1645123406,"sys":{"type":1,"id":7649,"country":"US","sunrise":1645124471,"sunset":1645150882},"timezone":-32400,"id":5880054,"name":"Barrow","cod":200},"pay-your-taxes-pickleball-showdown":{"coord":{"lon":-77.0349,"lat":38.8891},"weather":[{"id":804,"main":"Clouds","description":"overcast clouds","icon":"04d"}],"base":"stations","main":{"temp":291.98,"feels_like":291.64,"temp_min":288.68,"temp_max":294.59,"pressure":1015,"humidity":66},"visibility":10000,"wind":{"speed":7.2,"deg":200,"gust":11.32},"clouds":{"all":100},"dt":1645123406,"sys":{"type":2,"id":2017135,"country":"US","sunrise":1645099026,"sunset":1645138049},"timezone":-18000,"id":4140963,"name":"Washington D.C.","cod":200},"yet-another-new-event":{"coord":{"lon":-122.4232,"lat":37.7587},"weather":[{"id":800,"main":"Clear","description":"clear sky","icon":"01d"}],"base":"stations","main":{"temp":289.29,"feels_like":287.85,"temp_min":286.64,"temp_max":292.18,"pressure":1027,"humidity":34},"visibility":10000,"wind":{"speed":5.66,"deg":40,"gust":8.23},"clouds":{"all":0},"dt":1645123004,"sys":{"type":2,"id":2010146,"country":"US","sunrise":1645109820,"sunset":1645149040},"timezone":-28800,"id":5391959,"name":"San Francisco","cod":200}}
